intelurls/__init__.py
intelurls-0.0.5.dist-info/LICENSE.txt
intelurls-0.0.5.dist-info/METADATA
intelurls-0.0.5.dist-info/WHEEL
intelurls-0.0.5.dist-info/top_level.txt
intelurls-0.0.5.dist-info/RECORD
