Metadata-Version: 2.1
Name: intelurls
Version: 0.0.5
Summary: Parse Ingress Intel, Google Maps, and Apple Maps URLs
Home-page: https://gitlab.com/pleasantone/intelurls
Author: Paul Traina
Author-email: bulk+pypi@pst.org
License: UNKNOWN
Platform: UNKNOWN
Classifier: Development Status :: 3 - Alpha
Classifier: License :: OSI Approved :: GNU Affero General Public License v3 or later (AGPLv3+)
Classifier: Operating System :: POSIX
Classifier: Programming Language :: Python :: 3
Classifier: Topic :: Games/Entertainment
Requires-Dist: requests
Requires-Dist: geocoder
Provides-Extra: dev
Requires-Dist: check-manifest ; extra == 'dev'
Provides-Extra: test
Requires-Dist: coverage ; extra == 'test'
